myutils/__init__.py
myutils_canary-0.2.dist-info/licenses/LICENSE
myutils_canary-0.2.dist-info/METADATA
myutils_canary-0.2.dist-info/WHEEL
myutils_canary-0.2.dist-info/top_level.txt
myutils_canary-0.2.dist-info/RECORD
